<APIProxy revision="16" name="chatbot">
    <DisplayName></DisplayName>
    <Description></Description>
    <CreatedAt>1759728847584</CreatedAt>
    <LastModifiedAt>1759804179543</LastModifiedAt>
    <BasePaths>/chatbot</BasePaths>
    <Policies>
        <Policy>AM-TargetPath</Policy>
        <Policy>AM-SetTargetPath</Policy>
        <Policy>AM-SetAudience</Policy>
    </Policies>
    <ProxyEndpoints>
        <ProxyEndpoint>default</ProxyEndpoint>
    </ProxyEndpoints>
    <TargetEndpoints>
        <TargetEndpoint>default</TargetEndpoint>
    </TargetEndpoints>
</APIProxy>